yapyseq/__init__.py
yapyseq/cli.py
yapyseq/functiongrabber.py
yapyseq/nodes.py
yapyseq/seq_schema.yaml
yapyseq/sequencereader.py
yapyseq/sequencerunner.py
yapyseq-1.0.0.data/data/VERSION
yapyseq-1.0.0.dist-info/LICENSE
yapyseq-1.0.0.dist-info/METADATA
yapyseq-1.0.0.dist-info/WHEEL
yapyseq-1.0.0.dist-info/entry_points.txt
yapyseq-1.0.0.dist-info/top_level.txt
yapyseq-1.0.0.dist-info/RECORD
